orderbookzpy/__init__.py
orderbookzpy/client.py
orderbookzpy/direction.py
orderbookzpy/marketclient.py
orderbookzpy/tif.py
orderbookzpy-1.0.0.dist-info/METADATA
orderbookzpy-1.0.0.dist-info/WHEEL
orderbookzpy-1.0.0.dist-info/licenses/LICENSE
orderbookzpy-1.0.0.dist-info/RECORD
